README.md
setup.cfg
setup.py
py_piwik/__init__.py
py_piwik/goals.py
py_piwik/helpers.py
py_piwik/sites_manager.py
py_piwik/visits_summary.py
py_piwik.egg-info/PKG-INFO
py_piwik.egg-info/SOURCES.txt
py_piwik.egg-info/dependency_links.txt
py_piwik.egg-info/not-zip-safe
py_piwik.egg-info/requires.txt
py_piwik.egg-info/top_level.txt
py_piwik/tests/__init__.py
py_piwik/tests/test_sites_manager.py