Metadata-Version: 1.2
Name: py-piwik
Version: 0.1.4
Summary: Piwik API Client
Home-page: https://github.com/adminhead-tech/pypiwik
Author: AdminHead
Author-email: code@adminhead.tech
License: MIT
Keywords: piwik api client
Platform: UNKNOWN
Classifier: Intended Audience :: Developers
Classifier: Development Status :: 4 - Beta
Classifier: License :: OSI Approved :: MIT License
Classifier: Natural Language :: English
Classifier: Programming Language :: Python :: 3 :: Only
Requires-Python: >=3
